sgdotlite/__init__.py
sgdotlite/grids.py
sgdotlite/tools/__init__.py
sgdotlite/tools/grid_optimizer.py
sgdotlite/tools/io.py
sgdotlite/tools/plot.py
sgdotlite-1.0.33.dist-info/METADATA
sgdotlite-1.0.33.dist-info/WHEEL
sgdotlite-1.0.33.dist-info/top_level.txt
sgdotlite-1.0.33.dist-info/RECORD
