Metadata-Version: 2.1
Name: sgdotlite
Version: 1.0.33
Summary: UNKNOWN
Home-page: UNKNOWN
Author: UNKNOWN
Author-email: UNKNOWN
License: UNKNOWN
Platform: UNKNOWN
Requires-Dist: numpy
Requires-Dist: pandas
Requires-Dist: configparser
Requires-Dist: munkres
Requires-Dist: scipy
Requires-Dist: pulp
Requires-Dist: sklearn
Requires-Dist: matplotlib
